polars_vec_ops/__init__.py
polars_vec_ops/_internal.abi3.so
polars_vec_ops/_internal.pyi
polars_vec_ops/typing.py
polars_vec_ops-0.1.2.dist-info/METADATA
polars_vec_ops-0.1.2.dist-info/WHEEL
polars_vec_ops-0.1.2.dist-info/licenses/LICENSE
polars_vec_ops-0.1.2.dist-info/RECORD
