Metadata-Version: 2.4
Name: polars-vec-ops
Version: 0.1.2
Classifier: Development Status :: 3 - Alpha
Classifier: Programming Language :: Rust
Classifier: Programming Language :: Python :: Implementation :: CPython
Classifier: Programming Language :: Python :: Implementation :: PyPy
Classifier: License :: OSI Approved :: MIT License
Classifier: Operating System :: Microsoft :: Windows
Classifier: Operating System :: POSIX :: Linux
Classifier: Operating System :: MacOS :: MacOS X
Requires-Dist: polars>=1.8.0
License-File: LICENSE
Requires-Python: >=3.9
Project-URL: Issues, https://github.com/bjhardcastle/polars-vec-ops/issues
Project-URL: Repository, https://github.com/bjhardcastle/polars-vec-ops
